{"_id":"mustring","_rev":"13-ff0a2dfb5ae3f15dff0ac2d3d84c6fc3","name":"mustring","description":"Strings micro toolkit","dist-tags":{"latest":"1.0.0"},"versions":{"0.0.0":{"name":"mustring","version":"0.0.0","description":"Strings micro toolkit","main":"index.js","directories":{"test":"test"},"scripts":{"test":"echo \"Error: no test specified\" && exit 1"},"repository":{"type":"git","url":"git://github.com/dfcreative/mustring.git"},"keywords":["string","dashed","camel","upper","lower","capfirst"],"author":{"name":"dfcreative"},"license":"MIT","bugs":{"url":"https://github.com/dfcreative/mustring/issues"},"homepage":"https://github.com/dfcreative/mustring","_id":"mustring@0.0.0","dist":{"shasum":"127131e3ac6a0bdf5011a9c3a501f4b01f1af555","tarball":"https://registry.npmjs.org/mustring/-/mustring-0.0.0.tgz"},"_from":".","_npmVersion":"1.3.24","_npmUser":{"name":"dfcreative","email":"df.creative@gmail.com"},"maintainers":[{"name":"dfcreative","email":"df.creative@gmail.com"}]},"0.0.1":{"name":"mustring","version":"0.0.1","description":"Strings micro toolkit","main":"index.js","directories":{"test":"test"},"scripts":{"test":"echo \"Error: no test specified\" && exit 1"},"repository":{"type":"git","url":"git://github.com/dfcreative/mustring.git"},"keywords":["string","dashed","camel","upper","lower","capfirst"],"author":{"name":"dfcreative"},"license":"MIT","bugs":{"url":"https://github.com/dfcreative/mustring/issues"},"homepage":"https://github.com/dfcreative/mustring","_id":"mustring@0.0.1","dist":{"shasum":"4a4425f1a2fcb4b6c6a72231c104a7e788bb2c97","tarball":"https://registry.npmjs.org/mustring/-/mustring-0.0.1.tgz"},"_from":".","_npmVersion":"1.3.24","_npmUser":{"name":"dfcreative","email":"df.creative@gmail.com"},"maintainers":[{"name":"dfcreative","email":"df.creative@gmail.com"}]},"0.0.2":{"name":"mustring","version":"0.0.2","description":"Strings micro toolkit","main":"index.js","directories":{"test":"test"},"scripts":{"test":"node test/index.js"},"repository":{"type":"git","url":"git://github.com/dfcreative/mustring.git"},"keywords":["string","dashed","camel","upper","lower","capfirst"],"author":{"name":"dfcreative"},"license":"MIT","bugs":{"url":"https://github.com/dfcreative/mustring/issues"},"homepage":"https://github.com/dfcreative/mustring","_id":"mustring@0.0.2","dist":{"shasum":"6a01179377328ef9ac67dd21b11d65f4a6b95fcb","tarball":"https://registry.npmjs.org/mustring/-/mustring-0.0.2.tgz"},"_from":".","_npmVersion":"1.3.24","_npmUser":{"name":"dfcreative","email":"df.creative@gmail.com"},"maintainers":[{"name":"dfcreative","email":"df.creative@gmail.com"}]},"0.0.3":{"name":"mustring","version":"0.0.3","description":"Strings micro toolkit","main":"index.js","directories":{"test":"test"},"scripts":{"test":"node test/index.js"},"repository":{"type":"git","url":"git://github.com/dfcreative/mustring.git"},"keywords":["string","dashed","camel","upper","lower","capfirst"],"author":{"name":"dfcreative"},"license":"MIT","bugs":{"url":"https://github.com/dfcreative/mustring/issues"},"homepage":"https://github.com/dfcreative/mustring","_id":"mustring@0.0.3","dist":{"shasum":"2bfa9d328acc6d83cce048dcec222b13569ced06","tarball":"https://registry.npmjs.org/mustring/-/mustring-0.0.3.tgz"},"_from":".","_npmVersion":"1.3.24","_npmUser":{"name":"dfcreative","email":"df.creative@gmail.com"},"maintainers":[{"name":"dfcreative","email":"df.creative@gmail.com"}]},"0.0.4":{"name":"mustring","version":"0.0.4","description":"Strings micro toolkit","main":"index.js","directories":{"test":"test"},"scripts":{"test":"node test/index.js"},"repository":{"type":"git","url":"git://github.com/dfcreative/mustring.git"},"keywords":["string","dashed","camel","upper","lower","capfirst"],"author":{"name":"dfcreative"},"license":"MIT","bugs":{"url":"https://github.com/dfcreative/mustring/issues"},"homepage":"https://github.com/dfcreative/mustring","_id":"mustring@0.0.4","dist":{"shasum":"b36c1f4c7778a530904ced6f5416019ea4372159","tarball":"https://registry.npmjs.org/mustring/-/mustring-0.0.4.tgz"},"_from":".","_npmVersion":"1.3.24","_npmUser":{"name":"dfcreative","email":"df.creative@gmail.com"},"maintainers":[{"name":"dfcreative","email":"df.creative@gmail.com"}]},"0.0.5":{"name":"mustring","version":"0.0.5","description":"Strings micro toolkit","main":"index.js","directories":{"test":"test"},"files":["*.js"],"scripts":{"test":"node test/index.js"},"repository":{"type":"git","url":"git://github.com/dfcreative/mustring.git"},"keywords":["string","dashed","camel","upper","lower","capfirst"],"author":{"name":"dfcreative"},"license":"unlicense","bugs":{"url":"https://github.com/dfcreative/mustring/issues"},"homepage":"https://github.com/dfcreative/mustring","_id":"mustring@0.0.5","dist":{"shasum":"a64f18d0d6c26fe9e1820390ef8e04fbfb6f84a7","tarball":"https://registry.npmjs.org/mustring/-/mustring-0.0.5.tgz"},"_from":".","_npmVersion":"1.3.24","_npmUser":{"name":"dfcreative","email":"df.creative@gmail.com"},"maintainers":[{"name":"dfcreative","email":"df.creative@gmail.com"}]},"1.0.0":{"name":"mustring","version":"1.0.0","description":"Strings micro toolkit","main":"index.js","directories":{"test":"test"},"files":["*.js"],"scripts":{"test":"node test/index.js"},"repository":{"type":"git","url":"git://github.com/dfcreative/mustring.git"},"keywords":["string","dashed","camel","upper","lower","capfirst"],"author":{"name":"dfcreative"},"license":"unlicense","bugs":{"url":"https://github.com/dfcreative/mustring/issues"},"homepage":"https://github.com/dfcreative/mustring","gitHead":"c6d2517670238d8e1f4ffb82abbe15067cac2834","_id":"mustring@1.0.0","_shasum":"9d81dff9186c8fbefa5ef0e09339e87800af5bf2","_from":".","_npmVersion":"1.4.28","_npmUser":{"name":"dfcreative","email":"df.creative@gmail.com"},"maintainers":[{"name":"dfcreative","email":"df.creative@gmail.com"}],"dist":{"shasum":"9d81dff9186c8fbefa5ef0e09339e87800af5bf2","tarball":"https://registry.npmjs.org/mustring/-/mustring-1.0.0.tgz"}}},"readme":"# μString [![Build Status](https://travis-ci.org/dfcreative/mustring.svg?branch=master)](https://travis-ci.org/dfcreative/mustring) [![Code Climate](https://codeclimate.com/github/dfcreative/mustring/badges/gpa.svg)](https://codeclimate.com/github/dfcreative/mustring) <a href=\"UNLICENSE\"><img src=\"http://upload.wikimedia.org/wikipedia/commons/6/62/PD-icon.svg\" width=\"20\"/></a>\r\n\r\nMicro string utils:\r\n\r\n* `capfirst`\r\n* `dashed`\r\n* `camel`\r\n* `prefix(a, pfx)` - add prefix\r\n* `unprefix(a, pfx)` - remove prefix\r\n\r\nYou can require selectively as `require('mustring/<method>')`\r\n\r\n[![NPM](https://nodei.co/npm/mustring.png?downloads=true&downloadRank=true&stars=true)](https://nodei.co/npm/mustring/)","maintainers":[{"name":"dfcreative","email":"df.creative@gmail.com"}],"time":{"modified":"2015-10-19T15:52:55.212Z","created":"2014-08-27T08:54:50.201Z","0.0.0":"2014-08-27T08:54:50.201Z","0.0.1":"2014-09-07T22:38:50.298Z","0.0.2":"2014-11-27T16:26:35.077Z","0.0.3":"2014-12-04T00:42:50.139Z","0.0.4":"2014-12-10T20:25:39.885Z","0.0.5":"2014-12-14T15:31:45.634Z","1.0.0":"2015-10-19T15:52:55.212Z"},"homepage":"https://github.com/dfcreative/mustring","keywords":["string","dashed","camel","upper","lower","capfirst"],"repository":{"type":"git","url":"git://github.com/dfcreative/mustring.git"},"author":{"name":"dfcreative"},"bugs":{"url":"https://github.com/dfcreative/mustring/issues"},"license":"unlicense","readmeFilename":"README.md","_attachments":{},"_etag":"\"DPHTOIC3T9IRQ864SQAOG1TMP\""}